sample_mcp_test/__init__.py
sample_mcp_test/__main__.py
sample_mcp_test/mcp_test.py
sample_mcp_test-0.1.0.dist-info/METADATA
sample_mcp_test-0.1.0.dist-info/WHEEL
sample_mcp_test-0.1.0.dist-info/entry_points.txt
sample_mcp_test-0.1.0.dist-info/RECORD
