Metadata-Version: 2.4
Name: sample-mcp-test
Version: 0.1.0
Summary: Add your description here
Author-email: Gaurav Prasanna <gaurav.prasanna@thoughtclan.com>
Requires-Python: >=3.13
Requires-Dist: build>=1.2.2.post1
Requires-Dist: mcp[cli]>=1.9.4
Requires-Dist: twine>=6.1.0
